pgrsql2data/__init__.py
pgrsql2data/cli.py
pgrsql2data/main.py
pgrsql2data/version.py
pgrsql2data-19.2.1.dist-info/LICENSE
pgrsql2data-19.2.1.dist-info/METADATA
pgrsql2data-19.2.1.dist-info/WHEEL
pgrsql2data-19.2.1.dist-info/entry_points.txt
pgrsql2data-19.2.1.dist-info/top_level.txt
pgrsql2data-19.2.1.dist-info/RECORD
