Metadata-Version: 2.1
Name: pgrsql2data
Version: 19.2.1
Summary: Utility for converting PgRouting SQL scripts output by osm2po to data files (CSV, JSON or Avro).
Home-page: http://github.com/christippett/pgrsql2data
Author: Chris Tippett
Author-email: c.tippett@gmail.com
License: MIT
Keywords: osm2po pgrouting openstreetmap
Platform: UNKNOWN
Classifier: Environment :: Web Environment
Classifier: Operating System :: OS Independent
Classifier: License :: OSI Approved :: MIT License
Classifier: Programming Language :: Python
Classifier: Programming Language :: Python :: 3.5
Classifier: Programming Language :: Python :: 3.6
Classifier: Programming Language :: Python :: 3.7
Requires-Python: >=3
Requires-Dist: geomet
Requires-Dist: fastavro
